[
  {
    "title": "Котлеты из говяжьего и куриного фарша (без расплыва)",
    "category": "meat",
    "ingredients": [
      "Фарш говяжий — 400 г",
      "Фарш куриный — 400 г",
      "Лук — 1 большая луковица",
      "Чеснок — 2 зубчика",
      "Яйцо — 1 шт",
      "Панировочные сухари — 4 ст. л. (или 2–3 ст. л. манки)",
      "Вода/молоко — 0–2 ст. л. максимум",
      "Соль — 1,5 ч. л.",
      "Чёрный перец — по вкусу",
      "Паприка, зира, кориандр — по желанию",
      "Масло для жарки"
    ],
    "steps": [
      "Мелко нарежь лук и чеснок (можно обжарить).",
      "Смешай оба фарша, лук, чеснок, яйцо, сухари, соль, перец и специи.",
      "Хорошо вымешай руками 2–3 минуты.",
      "Накрой и убери в холодильник на 20–30 минут.",
      "Сформируй котлеты толщиной 1,5–2 см.",
      "Разогрей сковороду с маслом, обжаривай по 4–5 минут с каждой стороны.",
      "Убавь огонь, накрой крышкой и готовь ещё 5–7 минут."
    ],
    "metadata": {
      "servings": "4–6 (10–12 котлет среднего размера)",
      "equipment": "сковорода или духовка",
      "heat": "жарка на газу или запекание"
    }
  }

]
